angle_headings/__init__.py
angle_headings/_version.py
angle_headings/angles.py
angle_headings-1.1.1.dist-info/LICENSE
angle_headings-1.1.1.dist-info/METADATA
angle_headings-1.1.1.dist-info/WHEEL
angle_headings-1.1.1.dist-info/top_level.txt
angle_headings-1.1.1.dist-info/RECORD
