Metadata-Version: 2.1
Name: angle-headings
Version: 1.1.1
Summary: A class for representing and performing calculations with angles.
Home-page: https://github.com/adam-rumpf/angle-headings
Author: Adam Rumpf
Author-email: arumpf@floridapoly.edu
License: MIT
Project-URL: Source, https://github.com/adam-rumpf/angle-headings
Project-URL: Bug Tracker, https://github.com/adam-rumpf/angle-headings/issues
Keywords: angle,math,trigonometry
Platform: any
Classifier: Programming Language :: Python :: 3
Classifier: License :: OSI Approved :: MIT License
Classifier: Operating System :: OS Independent
Classifier: Development Status :: 5 - Production/Stable
Classifier: Intended Audience :: Developers
Classifier: Intended Audience :: Science/Research
Classifier: Topic :: Scientific/Engineering :: Mathematics
Classifier: Topic :: Utilities
Classifier: Natural Language :: English
License-File: LICENSE
